dragonfly_radiance/__init__.py
dragonfly_radiance/__main__.py
dragonfly_radiance/_extend_dragonfly.py
dragonfly_radiance/gridpar.py
dragonfly_radiance/cli/__init__.py
dragonfly_radiance/cli/translate.py
dragonfly_radiance/properties/__init__.py
dragonfly_radiance/properties/building.py
dragonfly_radiance/properties/context.py
dragonfly_radiance/properties/model.py
dragonfly_radiance/properties/room2d.py
dragonfly_radiance/properties/story.py
dragonfly_radiance-0.4.134.dist-info/licenses/LICENSE
dragonfly_radiance-0.4.134.dist-info/METADATA
dragonfly_radiance-0.4.134.dist-info/WHEEL
dragonfly_radiance-0.4.134.dist-info/entry_points.txt
dragonfly_radiance-0.4.134.dist-info/top_level.txt
dragonfly_radiance-0.4.134.dist-info/RECORD
